{"nodes": [{"id": "ceng222_week11_hypothesis", "label": "CENG222 Week 11: Hypothesis Testing", "file_type": "document", "source_file": "2-1/\u0130statistik ve Olas\u0131l\u0131k Hesaplar\u0131/slaytlar_notlar/2024/ceng222_week11.pdf", "source_location": null, "source_url": null, "captured_at": null, "author": null, "contributor": null}], "edges": [{"source": "ceng222_week11_hypothesis", "target": "ceng222_week10_estimation", "relation": "references", "confidence": "EXTRACTED", "confidence_score": 1.0, "source_file": "2-1/\u0130statistik ve Olas\u0131l\u0131k Hesaplar\u0131/slaytlar_notlar/2024/ceng222_week11.pdf", "source_location": null, "weight": 1.0}], "hyperedges": []}