{"nodes": [{"id": "kurul2_tutanak_img_0002", "label": "Proje \u00d6neri Listesi Sayfa 2", "file_type": "image", "source_file": "Bitirme \u00c7al\u0131\u015fmas\u0131/Esinlenmek \u0130\u00e7in Konular/2324_GUZ_KURUL2_TUTANAK-images/0002.jpg", "source_location": null, "source_url": null, "captured_at": null, "author": null, "contributor": null}], "edges": [{"source": "kurul2_tutanak_img_0002", "target": "kurul2_tutanak_img_0003", "relation": "semantically_similar_to", "confidence": "EXTRACTED", "confidence_score": 1.0, "source_file": "Bitirme \u00c7al\u0131\u015fmas\u0131/Esinlenmek \u0130\u00e7in Konular/2324_GUZ_KURUL2_TUTANAK-images/0002.jpg", "source_location": null, "weight": 1.0}], "hyperedges": []}