{"nodes": [{"id": "5_the_network_layer_control_plane_control_plane", "label": "The Network Layer - Control Plane", "file_type": "document", "source_file": "3-2/Veri \u0130leti\u015fimi ve Bilgisayar A\u011flar\u0131/a\u011f teknolojileri/slaytlar_notlar/2023/5-The Network Layer-Control Plane.pdf", "source_location": null, "source_url": null, "captured_at": null, "author": null, "contributor": null}], "edges": [{"source": "5_the_network_layer_control_plane_control_plane", "target": "4_the_network_layer_data_plane_data_plane", "relation": "conceptually_related_to", "confidence": "INFERRED", "confidence_score": 0.9, "source_file": "3-2/Veri \u0130leti\u015fimi ve Bilgisayar A\u011flar\u0131/a\u011f teknolojileri/slaytlar_notlar/2023/5-The Network Layer-Control Plane.pdf", "source_location": null, "weight": 1.0}], "hyperedges": []}