{"nodes": [{"id": "wrapper_analysis_report", "label": "Wrapper Analysis Report", "file_type": "document", "source_file": "Lisans\u00fcst\u00fc/Makine \u00d6\u011frenmesi/\u00f6devler/2024/2025/\u00f6dev2/kayra/kodlar/feature_selection/wrapper_analysis_report.md"}], "edges": [{"source": "wrapper_method_importance", "target": "wrapper_analysis_report", "relation": "conceptually_related_to", "confidence": "INFERRED", "confidence_score": 0.9, "source_file": "Lisans\u00fcst\u00fc/Makine \u00d6\u011frenmesi/\u00f6devler/2024/2025/\u00f6dev2/kayra/kodlar/feature_selection/wrapper_analysis_report.md"}], "hyperedges": []}