{"nodes": [{"id": "seslr_lab3_resource", "label": "Lab 3 Resource", "file_type": "document", "source_file": "3-1/Mikroi\u015flemci Sistemleri ve Assembly Dili/Mikroi\u015flemci Sistemleri/lablar/2022/lab3/kayra/seslr.pdf", "source_location": null, "source_url": null, "captured_at": null, "author": null, "contributor": null}], "edges": [{"source": "seslr_lab3_resource", "target": "soru_lab3_question", "relation": "references", "confidence": "INFERRED", "confidence_score": 0.8, "source_file": "3-1/Mikroi\u015flemci Sistemleri ve Assembly Dili/Mikroi\u015flemci Sistemleri/lablar/2022/lab3/kayra/seslr.pdf", "source_location": null, "weight": 1.0}], "hyperedges": []}