{"nodes": [{"id": "q3_mert_guler", "label": "Mert G\u00fcler Q3 Solution", "file_type": "document", "source_file": "2-2/Bilgisayar Organizasyonu/\u00f6devler/2025/\u00f6dev 2/mert_guler/Q3/q3.pdf", "source_location": null, "source_url": null, "captured_at": null, "author": "Mert G\u00fcler", "contributor": null}], "edges": [{"source": "q3_mert_guler", "target": "tanim_odev2_2025", "relation": "implements", "confidence": "INFERRED", "confidence_score": 0.9, "source_file": "2-2/Bilgisayar Organizasyonu/\u00f6devler/2025/\u00f6dev 2/mert_guler/Q3/q3.pdf", "source_location": null, "weight": 1.0}], "hyperedges": []}