{"nodes": [{"id": "bioinfo_06_lmsalignment_local_alignment", "label": "Local Multiple Sequence Alignment", "file_type": "document", "source_file": "Mesleki Se\u00e7meli 1/Biyoenformati\u011fe Giri\u015f/slaytlar/2023/bioinfo_06-lmsalignment.pdf", "source_location": null, "source_url": null, "captured_at": null, "author": null, "contributor": null}], "edges": [{"source": "bioinfo_05_gmsalignment_global_alignment", "target": "bioinfo_06_lmsalignment_local_alignment", "relation": "conceptually_related_to", "confidence": "EXTRACTED", "confidence_score": 1.0, "source_file": "Mesleki Se\u00e7meli 1/Biyoenformati\u011fe Giri\u015f/slaytlar/2023/bioinfo_06-lmsalignment.pdf", "source_location": null, "weight": 1.0}], "hyperedges": []}