{"nodes": [{"id": "rapor_student_report_yusuf", "label": "Student Report: Homework 2 (2022)", "file_type": "document", "source_file": "1-1/Bilgisayar Bilimlerine Giri\u015f/\u00f6devler/2022/\u00f6dev2/yusuf_safa_koksal/rapor.pdf", "source_location": null, "source_url": null, "captured_at": null, "author": "Yusuf Safa K\u00f6ksal", "contributor": null}], "edges": [{"source": "rapor_student_report_yusuf", "target": "tanim_homework1_definition", "relation": "references", "confidence": "AMBIGUOUS", "confidence_score": 0.5, "source_file": "1-1/Bilgisayar Bilimlerine Giri\u015f/\u00f6devler/2022/\u00f6dev2/yusuf_safa_koksal/rapor.pdf", "source_location": null, "weight": 1.0}], "hyperedges": []}