{"nodes": [{"id": "readme_2024", "label": "2024-2025 G\u00fcz D\u00f6nemi Ders Bilgileri", "file_type": "rationale", "source_file": "1-1/Bilgisayar Bilimlerine Giri\u015f/slaytlar_notlar/2024/README.md", "source_location": null, "source_url": null, "captured_at": null, "author": "G\u00f6ksel Biricik", "contributor": null}, {"id": "concept_algoritma_pratigi", "label": "Algoritma ve Ak\u0131\u015f Diyagram\u0131 Prati\u011fi", "file_type": "concept", "source_file": "1-1/Bilgisayar Bilimlerine Giri\u015f/slaytlar_notlar/2024/README.md", "source_location": null, "source_url": null, "captured_at": null, "author": null, "contributor": null}], "edges": [{"source": "readme_2024", "target": "bbg_slayt_1", "relation": "references", "confidence": "EXTRACTED", "confidence_score": 1.0, "source_file": "1-1/Bilgisayar Bilimlerine Giri\u015f/slaytlar_notlar/2024/README.md", "source_location": null, "weight": 1.0}, {"source": "readme_2024", "target": "bbg_slayt_10", "relation": "references", "confidence": "EXTRACTED", "confidence_score": 1.0, "source_file": "1-1/Bilgisayar Bilimlerine Giri\u015f/slaytlar_notlar/2024/README.md", "source_location": null, "weight": 1.0}, {"source": "readme_2024", "target": "bbg_slayt_2", "relation": "references", "confidence": "EXTRACTED", "confidence_score": 1.0, "source_file": "1-1/Bilgisayar Bilimlerine Giri\u015f/slaytlar_notlar/2024/README.md", "source_location": null, "weight": 1.0}, {"source": "readme_2024", "target": "bbg_slayt_3", "relation": "references", "confidence": "EXTRACTED", "confidence_score": 1.0, "source_file": "1-1/Bilgisayar Bilimlerine Giri\u015f/slaytlar_notlar/2024/README.md", "source_location": null, "weight": 1.0}, {"source": "bbg_slayt_1", "target": "concept_algoritma_pratigi", "relation": "conceptually_related_to", "confidence": "INFERRED", "confidence_score": 0.8, "source_file": "1-1/Bilgisayar Bilimlerine Giri\u015f/slaytlar_notlar/2024/README.md", "source_location": null, "weight": 1.0}], "hyperedges": []}