{"nodes": [{"id": "home_kayra_desktop_ytu_bilgisayar_muhendisligi_arsiv_lisans\u00fcst\u00fc_yaz\u0131l\u0131m_kalitesi_ve_test_teknikleri_readme_md", "label": "README.md", "file_type": "document", "source_file": "Lisans\u00fcst\u00fc/Yaz\u0131l\u0131m Kalitesi ve Test Teknikleri/README.md", "source_location": "L1"}, {"id": "yaz\u0131l\u0131m_kalitesi_ve_test_teknikleri_readme_yaz\u0131l\u0131m_kalitesi_ve_test_teknikleri", "label": "\ud83d\udcda Yaz\u0131l\u0131m Kalitesi ve Test Teknikleri", "file_type": "document", "source_file": "Lisans\u00fcst\u00fc/Yaz\u0131l\u0131m Kalitesi ve Test Teknikleri/README.md", "source_location": "L1"}, {"id": "yaz\u0131l\u0131m_kalitesi_ve_test_teknikleri_readme_i_ders_bilgileri", "label": "\u2139\ufe0f Ders Bilgileri", "file_type": "document", "source_file": "Lisans\u00fcst\u00fc/Yaz\u0131l\u0131m Kalitesi ve Test Teknikleri/README.md", "source_location": "L3"}, {"id": "yaz\u0131l\u0131m_kalitesi_ve_test_teknikleri_readme_faydal\u0131_olabilecek_kaynaklar", "label": "\ud83d\udcd6 Faydal\u0131 Olabilecek Kaynaklar", "file_type": "document", "source_file": "Lisans\u00fcst\u00fc/Yaz\u0131l\u0131m Kalitesi ve Test Teknikleri/README.md", "source_location": "L21"}, {"id": "yaz\u0131l\u0131m_kalitesi_ve_test_teknikleri_readme_dersi_y\u00fcr\u00fcten_akademisyenler", "label": "\ud83d\udc68\u200d\ud83c\udfeb \ud83d\udc69\u200d\ud83c\udfeb Dersi Y\u00fcr\u00fcten Akademisyenler:", "file_type": "document", "source_file": "Lisans\u00fcst\u00fc/Yaz\u0131l\u0131m Kalitesi ve Test Teknikleri/README.md", "source_location": "L26"}], "edges": [{"source": "home_kayra_desktop_ytu_bilgisayar_muhendisligi_arsiv_lisans\u00fcst\u00fc_yaz\u0131l\u0131m_kalitesi_ve_test_teknikleri_readme_md", "target": "yaz\u0131l\u0131m_kalitesi_ve_test_teknikleri_readme_yaz\u0131l\u0131m_kalitesi_ve_test_teknikleri", "relation": "contains", "confidence": "EXTRACTED", "source_file": "Lisans\u00fcst\u00fc/Yaz\u0131l\u0131m Kalitesi ve Test Teknikleri/README.md", "source_location": "L1", "weight": 1.0}, {"source": "yaz\u0131l\u0131m_kalitesi_ve_test_teknikleri_readme_yaz\u0131l\u0131m_kalitesi_ve_test_teknikleri", "target": "yaz\u0131l\u0131m_kalitesi_ve_test_teknikleri_readme_i_ders_bilgileri", "relation": "contains", "confidence": "EXTRACTED", "source_file": "Lisans\u00fcst\u00fc/Yaz\u0131l\u0131m Kalitesi ve Test Teknikleri/README.md", "source_location": "L3", "weight": 1.0}, {"source": "yaz\u0131l\u0131m_kalitesi_ve_test_teknikleri_readme_yaz\u0131l\u0131m_kalitesi_ve_test_teknikleri", "target": "yaz\u0131l\u0131m_kalitesi_ve_test_teknikleri_readme_faydal\u0131_olabilecek_kaynaklar", "relation": "contains", "confidence": "EXTRACTED", "source_file": "Lisans\u00fcst\u00fc/Yaz\u0131l\u0131m Kalitesi ve Test Teknikleri/README.md", "source_location": "L21", "weight": 1.0}, {"source": "yaz\u0131l\u0131m_kalitesi_ve_test_teknikleri_readme_yaz\u0131l\u0131m_kalitesi_ve_test_teknikleri", "target": "yaz\u0131l\u0131m_kalitesi_ve_test_teknikleri_readme_dersi_y\u00fcr\u00fcten_akademisyenler", "relation": "contains", "confidence": "EXTRACTED", "source_file": "Lisans\u00fcst\u00fc/Yaz\u0131l\u0131m Kalitesi ve Test Teknikleri/README.md", "source_location": "L26", "weight": 1.0}], "input_tokens": 0, "output_tokens": 0}