{"nodes": [{"id": "home_kayra_desktop_ytu_bilgisayar_muhendisligi_arsiv_mesleki_se\u00e7meli_1_blokzincir_temelleri_readme_md", "label": "README.md", "file_type": "document", "source_file": "Mesleki Se\u00e7meli 1/Blokzincir Temelleri/README.md", "source_location": "L1"}, {"id": "blokzincir_temelleri_readme_blokzincir_temelleri", "label": "\ud83d\udcda Blokzincir Temelleri", "file_type": "document", "source_file": "Mesleki Se\u00e7meli 1/Blokzincir Temelleri/README.md", "source_location": "L1"}, {"id": "blokzincir_temelleri_readme_i_ders_bilgileri", "label": "\u2139\ufe0f Ders Bilgileri", "file_type": "document", "source_file": "Mesleki Se\u00e7meli 1/Blokzincir Temelleri/README.md", "source_location": "L3"}, {"id": "blokzincir_temelleri_readme_faydal\u0131_olabilecek_kaynaklar", "label": "\ud83d\udcd6 Faydal\u0131 Olabilecek Kaynaklar", "file_type": "document", "source_file": "Mesleki Se\u00e7meli 1/Blokzincir Temelleri/README.md", "source_location": "L11"}, {"id": "blokzincir_temelleri_readme_dersi_y\u00fcr\u00fcten_akademisyenler", "label": "\ud83d\udc68\u200d\ud83c\udfeb \ud83d\udc69\u200d\ud83c\udfeb Dersi Y\u00fcr\u00fcten Akademisyenler:", "file_type": "document", "source_file": "Mesleki Se\u00e7meli 1/Blokzincir Temelleri/README.md", "source_location": "L17"}, {"id": "blokzincir_temelleri_readme_i\u0307\u00e7erik_yok", "label": "\ud83d\ude14 \u0130\u00e7erik yok", "file_type": "document", "source_file": "Mesleki Se\u00e7meli 1/Blokzincir Temelleri/README.md", "source_location": "L20"}], "edges": [{"source": "home_kayra_desktop_ytu_bilgisayar_muhendisligi_arsiv_mesleki_se\u00e7meli_1_blokzincir_temelleri_readme_md", "target": "blokzincir_temelleri_readme_blokzincir_temelleri", "relation": "contains", "confidence": "EXTRACTED", "source_file": "Mesleki Se\u00e7meli 1/Blokzincir Temelleri/README.md", "source_location": "L1", "weight": 1.0}, {"source": "blokzincir_temelleri_readme_blokzincir_temelleri", "target": "blokzincir_temelleri_readme_i_ders_bilgileri", "relation": "contains", "confidence": "EXTRACTED", "source_file": "Mesleki Se\u00e7meli 1/Blokzincir Temelleri/README.md", "source_location": "L3", "weight": 1.0}, {"source": "blokzincir_temelleri_readme_blokzincir_temelleri", "target": "blokzincir_temelleri_readme_faydal\u0131_olabilecek_kaynaklar", "relation": "contains", "confidence": "EXTRACTED", "source_file": "Mesleki Se\u00e7meli 1/Blokzincir Temelleri/README.md", "source_location": "L11", "weight": 1.0}, {"source": "blokzincir_temelleri_readme_blokzincir_temelleri", "target": "blokzincir_temelleri_readme_dersi_y\u00fcr\u00fcten_akademisyenler", "relation": "contains", "confidence": "EXTRACTED", "source_file": "Mesleki Se\u00e7meli 1/Blokzincir Temelleri/README.md", "source_location": "L17", "weight": 1.0}, {"source": "blokzincir_temelleri_readme_blokzincir_temelleri", "target": "blokzincir_temelleri_readme_i\u0307\u00e7erik_yok", "relation": "contains", "confidence": "EXTRACTED", "source_file": "Mesleki Se\u00e7meli 1/Blokzincir Temelleri/README.md", "source_location": "L20", "weight": 1.0}], "input_tokens": 0, "output_tokens": 0}