{"nodes": [{"id": "home_kayra_desktop_ytu_bilgisayar_muhendisligi_arsiv_1_2_say\u0131sal_analiz_readme_md", "label": "README.md", "file_type": "document", "source_file": "1-2/Say\u0131sal Analiz/README.md", "source_location": "L1"}, {"id": "say\u0131sal_analiz_readme_say\u0131sal_analiz", "label": "\ud83d\udcda Say\u0131sal Analiz", "file_type": "document", "source_file": "1-2/Say\u0131sal Analiz/README.md", "source_location": "L1"}, {"id": "say\u0131sal_analiz_readme_i_ders_bilgileri", "label": "\u2139\ufe0f Ders Bilgileri", "file_type": "document", "source_file": "1-2/Say\u0131sal Analiz/README.md", "source_location": "L3"}, {"id": "say\u0131sal_analiz_readme_faydal\u0131_olabilecek_kaynaklar", "label": "\ud83d\udcd6 Faydal\u0131 Olabilecek Kaynaklar", "file_type": "document", "source_file": "1-2/Say\u0131sal Analiz/README.md", "source_location": "L29"}, {"id": "say\u0131sal_analiz_readme_dersi_y\u00fcr\u00fcten_akademisyenler", "label": "\ud83d\udc68\u200d\ud83c\udfeb \ud83d\udc69\u200d\ud83c\udfeb Dersi Y\u00fcr\u00fcten Akademisyenler:", "file_type": "document", "source_file": "1-2/Say\u0131sal Analiz/README.md", "source_location": "L35"}], "edges": [{"source": "home_kayra_desktop_ytu_bilgisayar_muhendisligi_arsiv_1_2_say\u0131sal_analiz_readme_md", "target": "say\u0131sal_analiz_readme_say\u0131sal_analiz", "relation": "contains", "confidence": "EXTRACTED", "source_file": "1-2/Say\u0131sal Analiz/README.md", "source_location": "L1", "weight": 1.0}, {"source": "say\u0131sal_analiz_readme_say\u0131sal_analiz", "target": "say\u0131sal_analiz_readme_i_ders_bilgileri", "relation": "contains", "confidence": "EXTRACTED", "source_file": "1-2/Say\u0131sal Analiz/README.md", "source_location": "L3", "weight": 1.0}, {"source": "say\u0131sal_analiz_readme_say\u0131sal_analiz", "target": "say\u0131sal_analiz_readme_faydal\u0131_olabilecek_kaynaklar", "relation": "contains", "confidence": "EXTRACTED", "source_file": "1-2/Say\u0131sal Analiz/README.md", "source_location": "L29", "weight": 1.0}, {"source": "say\u0131sal_analiz_readme_say\u0131sal_analiz", "target": "say\u0131sal_analiz_readme_dersi_y\u00fcr\u00fcten_akademisyenler", "relation": "contains", "confidence": "EXTRACTED", "source_file": "1-2/Say\u0131sal Analiz/README.md", "source_location": "L35", "weight": 1.0}], "input_tokens": 0, "output_tokens": 0}