{"nodes": [{"id": "home_kayra_desktop_ytu_bilgisayar_muhendisligi_arsiv_lisans\u00fcst\u00fc_biyomedikal_i\u0307\u015faret_ve_g\u00f6r\u00fcnt\u00fc_i\u0307\u015fleme_\u00f6devler_2025_\u00f6dev6_kayra_kod_py", "label": "kod.py", "file_type": "code", "source_file": "Lisans\u00fcst\u00fc/Biyomedikal \u0130\u015faret ve G\u00f6r\u00fcnt\u00fc \u0130\u015fleme/\u00f6devler/2025/\u00f6dev6/kayra/kod.py", "source_location": "L1"}, {"id": "kayra_kod_ensure_dest_dir", "label": "ensure_dest_dir()", "file_type": "code", "source_file": "Lisans\u00fcst\u00fc/Biyomedikal \u0130\u015faret ve G\u00f6r\u00fcnt\u00fc \u0130\u015fleme/\u00f6devler/2025/\u00f6dev6/kayra/kod.py", "source_location": "L14"}, {"id": "kayra_kod_load_gray_images", "label": "load_gray_images()", "file_type": "code", "source_file": "Lisans\u00fcst\u00fc/Biyomedikal \u0130\u015faret ve G\u00f6r\u00fcnt\u00fc \u0130\u015fleme/\u00f6devler/2025/\u00f6dev6/kayra/kod.py", "source_location": "L18"}, {"id": "path", "label": "Path", "file_type": "code", "source_file": "Lisans\u00fcst\u00fc/Biyomedikal \u0130\u015faret ve G\u00f6r\u00fcnt\u00fc \u0130\u015fleme/\u00f6devler/2025/\u00f6dev6/kayra/kod.py", "source_location": "L18"}, {"id": "kayra_kod_compute_histogram", "label": "compute_histogram()", "file_type": "code", "source_file": "Lisans\u00fcst\u00fc/Biyomedikal \u0130\u015faret ve G\u00f6r\u00fcnt\u00fc \u0130\u015fleme/\u00f6devler/2025/\u00f6dev6/kayra/kod.py", "source_location": "L31"}, {"id": "ndarray", "label": "ndarray", "file_type": "code", "source_file": "Lisans\u00fcst\u00fc/Biyomedikal \u0130\u015faret ve G\u00f6r\u00fcnt\u00fc \u0130\u015fleme/\u00f6devler/2025/\u00f6dev6/kayra/kod.py", "source_location": "L31"}, {"id": "kayra_kod_compute_cumulative_histogram", "label": "compute_cumulative_histogram()", "file_type": "code", "source_file": "Lisans\u00fcst\u00fc/Biyomedikal \u0130\u015faret ve G\u00f6r\u00fcnt\u00fc \u0130\u015fleme/\u00f6devler/2025/\u00f6dev6/kayra/kod.py", "source_location": "L36"}, {"id": "kayra_kod_save_hist_and_cumulative", "label": "save_hist_and_cumulative()", "file_type": "code", "source_file": "Lisans\u00fcst\u00fc/Biyomedikal \u0130\u015faret ve G\u00f6r\u00fcnt\u00fc \u0130\u015fleme/\u00f6devler/2025/\u00f6dev6/kayra/kod.py", "source_location": "L40"}, {"id": "kayra_kod_linear_hist_equalization", "label": "linear_hist_equalization()", "file_type": "code", "source_file": "Lisans\u00fcst\u00fc/Biyomedikal \u0130\u015faret ve G\u00f6r\u00fcnt\u00fc \u0130\u015fleme/\u00f6devler/2025/\u00f6dev6/kayra/kod.py", "source_location": "L58"}, {"id": "kayra_kod_save_image", "label": "save_image()", "file_type": "code", "source_file": "Lisans\u00fcst\u00fc/Biyomedikal \u0130\u015faret ve G\u00f6r\u00fcnt\u00fc \u0130\u015fleme/\u00f6devler/2025/\u00f6dev6/kayra/kod.py", "source_location": "L62"}, {"id": "kayra_kod_histogram_specification", "label": "histogram_specification()", "file_type": "code", "source_file": "Lisans\u00fcst\u00fc/Biyomedikal \u0130\u015faret ve G\u00f6r\u00fcnt\u00fc \u0130\u015fleme/\u00f6devler/2025/\u00f6dev6/kayra/kod.py", "source_location": "L67"}, {"id": "kayra_kod_histogram_matching_cv", "label": "histogram_matching_cv()", "file_type": "code", "source_file": "Lisans\u00fcst\u00fc/Biyomedikal \u0130\u015faret ve G\u00f6r\u00fcnt\u00fc \u0130\u015fleme/\u00f6devler/2025/\u00f6dev6/kayra/kod.py", "source_location": "L89"}, {"id": "kayra_kod_main", "label": "main()", "file_type": "code", "source_file": "Lisans\u00fcst\u00fc/Biyomedikal \u0130\u015faret ve G\u00f6r\u00fcnt\u00fc \u0130\u015fleme/\u00f6devler/2025/\u00f6dev6/kayra/kod.py", "source_location": "L94"}], "edges": [{"source": "home_kayra_desktop_ytu_bilgisayar_muhendisligi_arsiv_lisans\u00fcst\u00fc_biyomedikal_i\u0307\u015faret_ve_g\u00f6r\u00fcnt\u00fc_i\u0307\u015fleme_\u00f6devler_2025_\u00f6dev6_kayra_kod_py", "target": "os", "relation": "imports", "context": "import", "confidence": "EXTRACTED", "source_file": "Lisans\u00fcst\u00fc/Biyomedikal \u0130\u015faret ve G\u00f6r\u00fcnt\u00fc \u0130\u015fleme/\u00f6devler/2025/\u00f6dev6/kayra/kod.py", "source_location": "L1", "weight": 1.0}, {"source": "home_kayra_desktop_ytu_bilgisayar_muhendisligi_arsiv_lisans\u00fcst\u00fc_biyomedikal_i\u0307\u015faret_ve_g\u00f6r\u00fcnt\u00fc_i\u0307\u015fleme_\u00f6devler_2025_\u00f6dev6_kayra_kod_py", "target": "pathlib", "relation": "imports_from", "context": "import", "confidence": "EXTRACTED", "source_file": "Lisans\u00fcst\u00fc/Biyomedikal \u0130\u015faret ve G\u00f6r\u00fcnt\u00fc \u0130\u015fleme/\u00f6devler/2025/\u00f6dev6/kayra/kod.py", "source_location": "L2", "weight": 1.0}, {"source": "home_kayra_desktop_ytu_bilgisayar_muhendisligi_arsiv_lisans\u00fcst\u00fc_biyomedikal_i\u0307\u015faret_ve_g\u00f6r\u00fcnt\u00fc_i\u0307\u015fleme_\u00f6devler_2025_\u00f6dev6_kayra_kod_py", "target": "cv2", "relation": "imports", "context": "import", "confidence": "EXTRACTED", "source_file": "Lisans\u00fcst\u00fc/Biyomedikal \u0130\u015faret ve G\u00f6r\u00fcnt\u00fc \u0130\u015fleme/\u00f6devler/2025/\u00f6dev6/kayra/kod.py", "source_location": "L4", "weight": 1.0}, {"source": "home_kayra_desktop_ytu_bilgisayar_muhendisligi_arsiv_lisans\u00fcst\u00fc_biyomedikal_i\u0307\u015faret_ve_g\u00f6r\u00fcnt\u00fc_i\u0307\u015fleme_\u00f6devler_2025_\u00f6dev6_kayra_kod_py", "target": "numpy", "relation": "imports", "context": "import", "confidence": "EXTRACTED", "source_file": "Lisans\u00fcst\u00fc/Biyomedikal \u0130\u015faret ve G\u00f6r\u00fcnt\u00fc \u0130\u015fleme/\u00f6devler/2025/\u00f6dev6/kayra/kod.py", "source_location": "L5", "weight": 1.0}, {"source": "home_kayra_desktop_ytu_bilgisayar_muhendisligi_arsiv_lisans\u00fcst\u00fc_biyomedikal_i\u0307\u015faret_ve_g\u00f6r\u00fcnt\u00fc_i\u0307\u015fleme_\u00f6devler_2025_\u00f6dev6_kayra_kod_py", "target": "matplotlib", "relation": "imports_from", "context": "import", "confidence": "EXTRACTED", "source_file": "Lisans\u00fcst\u00fc/Biyomedikal \u0130\u015faret ve G\u00f6r\u00fcnt\u00fc \u0130\u015fleme/\u00f6devler/2025/\u00f6dev6/kayra/kod.py", "source_location": "L6", "weight": 1.0}, {"source": "home_kayra_desktop_ytu_bilgisayar_muhendisligi_arsiv_lisans\u00fcst\u00fc_biyomedikal_i\u0307\u015faret_ve_g\u00f6r\u00fcnt\u00fc_i\u0307\u015fleme_\u00f6devler_2025_\u00f6dev6_kayra_kod_py", "target": "kayra_kod_ensure_dest_dir", "relation": "contains", "confidence": "EXTRACTED", "source_file": "Lisans\u00fcst\u00fc/Biyomedikal \u0130\u015faret ve G\u00f6r\u00fcnt\u00fc \u0130\u015fleme/\u00f6devler/2025/\u00f6dev6/kayra/kod.py", "source_location": "L14", "weight": 1.0}, {"source": "home_kayra_desktop_ytu_bilgisayar_muhendisligi_arsiv_lisans\u00fcst\u00fc_biyomedikal_i\u0307\u015faret_ve_g\u00f6r\u00fcnt\u00fc_i\u0307\u015fleme_\u00f6devler_2025_\u00f6dev6_kayra_kod_py", "target": "kayra_kod_load_gray_images", "relation": "contains", "confidence": "EXTRACTED", "source_file": "Lisans\u00fcst\u00fc/Biyomedikal \u0130\u015faret ve G\u00f6r\u00fcnt\u00fc \u0130\u015fleme/\u00f6devler/2025/\u00f6dev6/kayra/kod.py", "source_location": "L18", "weight": 1.0}, {"source": "kayra_kod_load_gray_images", "target": "path", "relation": "references", "context": "parameter_type", "confidence": "EXTRACTED", "source_file": "Lisans\u00fcst\u00fc/Biyomedikal \u0130\u015faret ve G\u00f6r\u00fcnt\u00fc \u0130\u015fleme/\u00f6devler/2025/\u00f6dev6/kayra/kod.py", "source_location": "L18", "weight": 1.0}, {"source": "home_kayra_desktop_ytu_bilgisayar_muhendisligi_arsiv_lisans\u00fcst\u00fc_biyomedikal_i\u0307\u015faret_ve_g\u00f6r\u00fcnt\u00fc_i\u0307\u015fleme_\u00f6devler_2025_\u00f6dev6_kayra_kod_py", "target": "kayra_kod_compute_histogram", "relation": "contains", "confidence": "EXTRACTED", "source_file": "Lisans\u00fcst\u00fc/Biyomedikal \u0130\u015faret ve G\u00f6r\u00fcnt\u00fc \u0130\u015fleme/\u00f6devler/2025/\u00f6dev6/kayra/kod.py", "source_location": "L31", "weight": 1.0}, {"source": "kayra_kod_compute_histogram", "target": "ndarray", "relation": "references", "context": "parameter_type", "confidence": "EXTRACTED", "source_file": "Lisans\u00fcst\u00fc/Biyomedikal \u0130\u015faret ve G\u00f6r\u00fcnt\u00fc \u0130\u015fleme/\u00f6devler/2025/\u00f6dev6/kayra/kod.py", "source_location": "L31", "weight": 1.0}, {"source": "home_kayra_desktop_ytu_bilgisayar_muhendisligi_arsiv_lisans\u00fcst\u00fc_biyomedikal_i\u0307\u015faret_ve_g\u00f6r\u00fcnt\u00fc_i\u0307\u015fleme_\u00f6devler_2025_\u00f6dev6_kayra_kod_py", "target": "kayra_kod_compute_cumulative_histogram", "relation": "contains", "confidence": "EXTRACTED", "source_file": "Lisans\u00fcst\u00fc/Biyomedikal \u0130\u015faret ve G\u00f6r\u00fcnt\u00fc \u0130\u015fleme/\u00f6devler/2025/\u00f6dev6/kayra/kod.py", "source_location": "L36", "weight": 1.0}, {"source": "kayra_kod_compute_cumulative_histogram", "target": "ndarray", "relation": "references", "context": "parameter_type", "confidence": "EXTRACTED", "source_file": "Lisans\u00fcst\u00fc/Biyomedikal \u0130\u015faret ve G\u00f6r\u00fcnt\u00fc \u0130\u015fleme/\u00f6devler/2025/\u00f6dev6/kayra/kod.py", "source_location": "L36", "weight": 1.0}, {"source": "home_kayra_desktop_ytu_bilgisayar_muhendisligi_arsiv_lisans\u00fcst\u00fc_biyomedikal_i\u0307\u015faret_ve_g\u00f6r\u00fcnt\u00fc_i\u0307\u015fleme_\u00f6devler_2025_\u00f6dev6_kayra_kod_py", "target": "kayra_kod_save_hist_and_cumulative", "relation": "contains", "confidence": "EXTRACTED", "source_file": "Lisans\u00fcst\u00fc/Biyomedikal \u0130\u015faret ve G\u00f6r\u00fcnt\u00fc \u0130\u015fleme/\u00f6devler/2025/\u00f6dev6/kayra/kod.py", "source_location": "L40", "weight": 1.0}, {"source": "kayra_kod_save_hist_and_cumulative", "target": "ndarray", "relation": "references", "context": "parameter_type", "confidence": "EXTRACTED", "source_file": "Lisans\u00fcst\u00fc/Biyomedikal \u0130\u015faret ve G\u00f6r\u00fcnt\u00fc \u0130\u015fleme/\u00f6devler/2025/\u00f6dev6/kayra/kod.py", "source_location": "L40", "weight": 1.0}, {"source": "kayra_kod_save_hist_and_cumulative", "target": "ndarray", "relation": "references", "context": "parameter_type", "confidence": "EXTRACTED", "source_file": "Lisans\u00fcst\u00fc/Biyomedikal \u0130\u015faret ve G\u00f6r\u00fcnt\u00fc \u0130\u015fleme/\u00f6devler/2025/\u00f6dev6/kayra/kod.py", "source_location": "L40", "weight": 1.0}, {"source": "home_kayra_desktop_ytu_bilgisayar_muhendisligi_arsiv_lisans\u00fcst\u00fc_biyomedikal_i\u0307\u015faret_ve_g\u00f6r\u00fcnt\u00fc_i\u0307\u015fleme_\u00f6devler_2025_\u00f6dev6_kayra_kod_py", "target": "kayra_kod_linear_hist_equalization", "relation": "contains", "confidence": "EXTRACTED", "source_file": "Lisans\u00fcst\u00fc/Biyomedikal \u0130\u015faret ve G\u00f6r\u00fcnt\u00fc \u0130\u015fleme/\u00f6devler/2025/\u00f6dev6/kayra/kod.py", "source_location": "L58", "weight": 1.0}, {"source": "kayra_kod_linear_hist_equalization", "target": "ndarray", "relation": "references", "context": "parameter_type", "confidence": "EXTRACTED", "source_file": "Lisans\u00fcst\u00fc/Biyomedikal \u0130\u015faret ve G\u00f6r\u00fcnt\u00fc \u0130\u015fleme/\u00f6devler/2025/\u00f6dev6/kayra/kod.py", "source_location": "L58", "weight": 1.0}, {"source": "home_kayra_desktop_ytu_bilgisayar_muhendisligi_arsiv_lisans\u00fcst\u00fc_biyomedikal_i\u0307\u015faret_ve_g\u00f6r\u00fcnt\u00fc_i\u0307\u015fleme_\u00f6devler_2025_\u00f6dev6_kayra_kod_py", "target": "kayra_kod_save_image", "relation": "contains", "confidence": "EXTRACTED", "source_file": "Lisans\u00fcst\u00fc/Biyomedikal \u0130\u015faret ve G\u00f6r\u00fcnt\u00fc \u0130\u015fleme/\u00f6devler/2025/\u00f6dev6/kayra/kod.py", "source_location": "L62", "weight": 1.0}, {"source": "kayra_kod_save_image", "target": "ndarray", "relation": "references", "context": "parameter_type", "confidence": "EXTRACTED", "source_file": "Lisans\u00fcst\u00fc/Biyomedikal \u0130\u015faret ve G\u00f6r\u00fcnt\u00fc \u0130\u015fleme/\u00f6devler/2025/\u00f6dev6/kayra/kod.py", "source_location": "L62", "weight": 1.0}, {"source": "home_kayra_desktop_ytu_bilgisayar_muhendisligi_arsiv_lisans\u00fcst\u00fc_biyomedikal_i\u0307\u015faret_ve_g\u00f6r\u00fcnt\u00fc_i\u0307\u015fleme_\u00f6devler_2025_\u00f6dev6_kayra_kod_py", "target": "kayra_kod_histogram_specification", "relation": "contains", "confidence": "EXTRACTED", "source_file": "Lisans\u00fcst\u00fc/Biyomedikal \u0130\u015faret ve G\u00f6r\u00fcnt\u00fc \u0130\u015fleme/\u00f6devler/2025/\u00f6dev6/kayra/kod.py", "source_location": "L67", "weight": 1.0}, {"source": "kayra_kod_histogram_specification", "target": "ndarray", "relation": "references", "context": "parameter_type", "confidence": "EXTRACTED", "source_file": "Lisans\u00fcst\u00fc/Biyomedikal \u0130\u015faret ve G\u00f6r\u00fcnt\u00fc \u0130\u015fleme/\u00f6devler/2025/\u00f6dev6/kayra/kod.py", "source_location": "L67", "weight": 1.0}, {"source": "kayra_kod_histogram_specification", "target": "ndarray", "relation": "references", "context": "parameter_type", "confidence": "EXTRACTED", "source_file": "Lisans\u00fcst\u00fc/Biyomedikal \u0130\u015faret ve G\u00f6r\u00fcnt\u00fc \u0130\u015fleme/\u00f6devler/2025/\u00f6dev6/kayra/kod.py", "source_location": "L67", "weight": 1.0}, {"source": "home_kayra_desktop_ytu_bilgisayar_muhendisligi_arsiv_lisans\u00fcst\u00fc_biyomedikal_i\u0307\u015faret_ve_g\u00f6r\u00fcnt\u00fc_i\u0307\u015fleme_\u00f6devler_2025_\u00f6dev6_kayra_kod_py", "target": "kayra_kod_histogram_matching_cv", "relation": "contains", "confidence": "EXTRACTED", "source_file": "Lisans\u00fcst\u00fc/Biyomedikal \u0130\u015faret ve G\u00f6r\u00fcnt\u00fc \u0130\u015fleme/\u00f6devler/2025/\u00f6dev6/kayra/kod.py", "source_location": "L89", "weight": 1.0}, {"source": "kayra_kod_histogram_matching_cv", "target": "ndarray", "relation": "references", "context": "parameter_type", "confidence": "EXTRACTED", "source_file": "Lisans\u00fcst\u00fc/Biyomedikal \u0130\u015faret ve G\u00f6r\u00fcnt\u00fc \u0130\u015fleme/\u00f6devler/2025/\u00f6dev6/kayra/kod.py", "source_location": "L89", "weight": 1.0}, {"source": "kayra_kod_histogram_matching_cv", "target": "ndarray", "relation": "references", "context": "parameter_type", "confidence": "EXTRACTED", "source_file": "Lisans\u00fcst\u00fc/Biyomedikal \u0130\u015faret ve G\u00f6r\u00fcnt\u00fc \u0130\u015fleme/\u00f6devler/2025/\u00f6dev6/kayra/kod.py", "source_location": "L89", "weight": 1.0}, {"source": "home_kayra_desktop_ytu_bilgisayar_muhendisligi_arsiv_lisans\u00fcst\u00fc_biyomedikal_i\u0307\u015faret_ve_g\u00f6r\u00fcnt\u00fc_i\u0307\u015fleme_\u00f6devler_2025_\u00f6dev6_kayra_kod_py", "target": "kayra_kod_main", "relation": "contains", "confidence": "EXTRACTED", "source_file": "Lisans\u00fcst\u00fc/Biyomedikal \u0130\u015faret ve G\u00f6r\u00fcnt\u00fc \u0130\u015fleme/\u00f6devler/2025/\u00f6dev6/kayra/kod.py", "source_location": "L94", "weight": 1.0}, {"source": "kayra_kod_histogram_matching_cv", "target": "kayra_kod_histogram_specification", "relation": "calls", "context": "call", "confidence": "EXTRACTED", "source_file": "Lisans\u00fcst\u00fc/Biyomedikal \u0130\u015faret ve G\u00f6r\u00fcnt\u00fc \u0130\u015fleme/\u00f6devler/2025/\u00f6dev6/kayra/kod.py", "source_location": "L91", "weight": 1.0}, {"source": "kayra_kod_main", "target": "kayra_kod_ensure_dest_dir", "relation": "calls", "context": "call", "confidence": "EXTRACTED", "source_file": "Lisans\u00fcst\u00fc/Biyomedikal \u0130\u015faret ve G\u00f6r\u00fcnt\u00fc \u0130\u015fleme/\u00f6devler/2025/\u00f6dev6/kayra/kod.py", "source_location": "L95", "weight": 1.0}, {"source": "kayra_kod_main", "target": "kayra_kod_load_gray_images", "relation": "calls", "context": "call", "confidence": "EXTRACTED", "source_file": "Lisans\u00fcst\u00fc/Biyomedikal \u0130\u015faret ve G\u00f6r\u00fcnt\u00fc \u0130\u015fleme/\u00f6devler/2025/\u00f6dev6/kayra/kod.py", "source_location": "L97", "weight": 1.0}, {"source": "kayra_kod_main", "target": "kayra_kod_compute_histogram", "relation": "calls", "context": "call", "confidence": "EXTRACTED", "source_file": "Lisans\u00fcst\u00fc/Biyomedikal \u0130\u015faret ve G\u00f6r\u00fcnt\u00fc \u0130\u015fleme/\u00f6devler/2025/\u00f6dev6/kayra/kod.py", "source_location": "L103", "weight": 1.0}, {"source": "kayra_kod_main", "target": "kayra_kod_compute_cumulative_histogram", "relation": "calls", "context": "call", "confidence": "EXTRACTED", "source_file": "Lisans\u00fcst\u00fc/Biyomedikal \u0130\u015faret ve G\u00f6r\u00fcnt\u00fc \u0130\u015fleme/\u00f6devler/2025/\u00f6dev6/kayra/kod.py", "source_location": "L104", "weight": 1.0}, {"source": "kayra_kod_main", "target": "kayra_kod_save_hist_and_cumulative", "relation": "calls", "context": "call", "confidence": "EXTRACTED", "source_file": "Lisans\u00fcst\u00fc/Biyomedikal \u0130\u015faret ve G\u00f6r\u00fcnt\u00fc \u0130\u015fleme/\u00f6devler/2025/\u00f6dev6/kayra/kod.py", "source_location": "L105", "weight": 1.0}, {"source": "kayra_kod_main", "target": "path", "relation": "calls", "context": "call", "confidence": "EXTRACTED", "source_file": "Lisans\u00fcst\u00fc/Biyomedikal \u0130\u015faret ve G\u00f6r\u00fcnt\u00fc \u0130\u015fleme/\u00f6devler/2025/\u00f6dev6/kayra/kod.py", "source_location": "L105", "weight": 1.0}, {"source": "kayra_kod_main", "target": "kayra_kod_linear_hist_equalization", "relation": "calls", "context": "call", "confidence": "EXTRACTED", "source_file": "Lisans\u00fcst\u00fc/Biyomedikal \u0130\u015faret ve G\u00f6r\u00fcnt\u00fc \u0130\u015fleme/\u00f6devler/2025/\u00f6dev6/kayra/kod.py", "source_location": "L110", "weight": 1.0}, {"source": "kayra_kod_main", "target": "kayra_kod_save_image", "relation": "calls", "context": "call", "confidence": "EXTRACTED", "source_file": "Lisans\u00fcst\u00fc/Biyomedikal \u0130\u015faret ve G\u00f6r\u00fcnt\u00fc \u0130\u015fleme/\u00f6devler/2025/\u00f6dev6/kayra/kod.py", "source_location": "L112", "weight": 1.0}, {"source": "kayra_kod_main", "target": "kayra_kod_histogram_specification", "relation": "calls", "context": "call", "confidence": "EXTRACTED", "source_file": "Lisans\u00fcst\u00fc/Biyomedikal \u0130\u015faret ve G\u00f6r\u00fcnt\u00fc \u0130\u015fleme/\u00f6devler/2025/\u00f6dev6/kayra/kod.py", "source_location": "L124", "weight": 1.0}, {"source": "kayra_kod_main", "target": "kayra_kod_histogram_matching_cv", "relation": "calls", "context": "call", "confidence": "EXTRACTED", "source_file": "Lisans\u00fcst\u00fc/Biyomedikal \u0130\u015faret ve G\u00f6r\u00fcnt\u00fc \u0130\u015fleme/\u00f6devler/2025/\u00f6dev6/kayra/kod.py", "source_location": "L136", "weight": 1.0}], "raw_calls": [{"caller_nid": "kayra_kod_ensure_dest_dir", "callee": "mkdir", "is_member_call": true, "source_file": "/home/kayra/Desktop/YTU_Bilgisayar_Muhendisligi_Arsiv/Lisans\u00fcst\u00fc/Biyomedikal \u0130\u015faret ve G\u00f6r\u00fcnt\u00fc \u0130\u015fleme/\u00f6devler/2025/\u00f6dev6/kayra/kod.py", "source_location": "L15"}, {"caller_nid": "kayra_kod_load_gray_images", "callee": "listdir", "is_member_call": true, "source_file": "/home/kayra/Desktop/YTU_Bilgisayar_Muhendisligi_Arsiv/Lisans\u00fcst\u00fc/Biyomedikal \u0130\u015faret ve G\u00f6r\u00fcnt\u00fc \u0130\u015fleme/\u00f6devler/2025/\u00f6dev6/kayra/kod.py", "source_location": "L20"}, {"caller_nid": "kayra_kod_load_gray_images", "callee": "is_file", "is_member_call": true, "source_file": "/home/kayra/Desktop/YTU_Bilgisayar_Muhendisligi_Arsiv/Lisans\u00fcst\u00fc/Biyomedikal \u0130\u015faret ve G\u00f6r\u00fcnt\u00fc \u0130\u015fleme/\u00f6devler/2025/\u00f6dev6/kayra/kod.py", "source_location": "L22"}, {"caller_nid": "kayra_kod_load_gray_images", "callee": "imread", "is_member_call": true, "source_file": "/home/kayra/Desktop/YTU_Bilgisayar_Muhendisligi_Arsiv/Lisans\u00fcst\u00fc/Biyomedikal \u0130\u015faret ve G\u00f6r\u00fcnt\u00fc \u0130\u015fleme/\u00f6devler/2025/\u00f6dev6/kayra/kod.py", "source_location": "L24"}, {"caller_nid": "kayra_kod_compute_histogram", "callee": "histogram", "is_member_call": true, "source_file": "/home/kayra/Desktop/YTU_Bilgisayar_Muhendisligi_Arsiv/Lisans\u00fcst\u00fc/Biyomedikal \u0130\u015faret ve G\u00f6r\u00fcnt\u00fc \u0130\u015fleme/\u00f6devler/2025/\u00f6dev6/kayra/kod.py", "source_location": "L32"}, {"caller_nid": "kayra_kod_compute_histogram", "callee": "flatten", "is_member_call": true, "source_file": "/home/kayra/Desktop/YTU_Bilgisayar_Muhendisligi_Arsiv/Lisans\u00fcst\u00fc/Biyomedikal \u0130\u015faret ve G\u00f6r\u00fcnt\u00fc \u0130\u015fleme/\u00f6devler/2025/\u00f6dev6/kayra/kod.py", "source_location": "L32"}, {"caller_nid": "kayra_kod_compute_cumulative_histogram", "callee": "cumsum", "is_member_call": true, "source_file": "/home/kayra/Desktop/YTU_Bilgisayar_Muhendisligi_Arsiv/Lisans\u00fcst\u00fc/Biyomedikal \u0130\u015faret ve G\u00f6r\u00fcnt\u00fc \u0130\u015fleme/\u00f6devler/2025/\u00f6dev6/kayra/kod.py", "source_location": "L37"}, {"caller_nid": "kayra_kod_save_hist_and_cumulative", "callee": "figure", "is_member_call": true, "source_file": "/home/kayra/Desktop/YTU_Bilgisayar_Muhendisligi_Arsiv/Lisans\u00fcst\u00fc/Biyomedikal \u0130\u015faret ve G\u00f6r\u00fcnt\u00fc \u0130\u015fleme/\u00f6devler/2025/\u00f6dev6/kayra/kod.py", "source_location": "L41"}, {"caller_nid": "kayra_kod_save_hist_and_cumulative", "callee": "subplot", "is_member_call": true, "source_file": "/home/kayra/Desktop/YTU_Bilgisayar_Muhendisligi_Arsiv/Lisans\u00fcst\u00fc/Biyomedikal \u0130\u015faret ve G\u00f6r\u00fcnt\u00fc \u0130\u015fleme/\u00f6devler/2025/\u00f6dev6/kayra/kod.py", "source_location": "L42"}, {"caller_nid": "kayra_kod_save_hist_and_cumulative", "callee": "title", "is_member_call": true, "source_file": "/home/kayra/Desktop/YTU_Bilgisayar_Muhendisligi_Arsiv/Lisans\u00fcst\u00fc/Biyomedikal \u0130\u015faret ve G\u00f6r\u00fcnt\u00fc \u0130\u015fleme/\u00f6devler/2025/\u00f6dev6/kayra/kod.py", "source_location": "L43"}, {"caller_nid": "kayra_kod_save_hist_and_cumulative", "callee": "plot", "is_member_call": true, "source_file": "/home/kayra/Desktop/YTU_Bilgisayar_Muhendisligi_Arsiv/Lisans\u00fcst\u00fc/Biyomedikal \u0130\u015faret ve G\u00f6r\u00fcnt\u00fc \u0130\u015fleme/\u00f6devler/2025/\u00f6dev6/kayra/kod.py", "source_location": "L44"}, {"caller_nid": "kayra_kod_save_hist_and_cumulative", "callee": "xlim", "is_member_call": true, "source_file": "/home/kayra/Desktop/YTU_Bilgisayar_Muhendisligi_Arsiv/Lisans\u00fcst\u00fc/Biyomedikal \u0130\u015faret ve G\u00f6r\u00fcnt\u00fc \u0130\u015fleme/\u00f6devler/2025/\u00f6dev6/kayra/kod.py", "source_location": "L45"}, {"caller_nid": "kayra_kod_save_hist_and_cumulative", "callee": "subplot", "is_member_call": true, "source_file": "/home/kayra/Desktop/YTU_Bilgisayar_Muhendisligi_Arsiv/Lisans\u00fcst\u00fc/Biyomedikal \u0130\u015faret ve G\u00f6r\u00fcnt\u00fc \u0130\u015fleme/\u00f6devler/2025/\u00f6dev6/kayra/kod.py", "source_location": "L47"}, {"caller_nid": "kayra_kod_save_hist_and_cumulative", "callee": "title", "is_member_call": true, "source_file": "/home/kayra/Desktop/YTU_Bilgisayar_Muhendisligi_Arsiv/Lisans\u00fcst\u00fc/Biyomedikal \u0130\u015faret ve G\u00f6r\u00fcnt\u00fc \u0130\u015fleme/\u00f6devler/2025/\u00f6dev6/kayra/kod.py", "source_location": "L48"}, {"caller_nid": "kayra_kod_save_hist_and_cumulative", "callee": "plot", "is_member_call": true, "source_file": "/home/kayra/Desktop/YTU_Bilgisayar_Muhendisligi_Arsiv/Lisans\u00fcst\u00fc/Biyomedikal \u0130\u015faret ve G\u00f6r\u00fcnt\u00fc \u0130\u015fleme/\u00f6devler/2025/\u00f6dev6/kayra/kod.py", "source_location": "L49"}, {"caller_nid": "kayra_kod_save_hist_and_cumulative", "callee": "xlim", "is_member_call": true, "source_file": "/home/kayra/Desktop/YTU_Bilgisayar_Muhendisligi_Arsiv/Lisans\u00fcst\u00fc/Biyomedikal \u0130\u015faret ve G\u00f6r\u00fcnt\u00fc \u0130\u015fleme/\u00f6devler/2025/\u00f6dev6/kayra/kod.py", "source_location": "L50"}, {"caller_nid": "kayra_kod_save_hist_and_cumulative", "callee": "tight_layout", "is_member_call": true, "source_file": "/home/kayra/Desktop/YTU_Bilgisayar_Muhendisligi_Arsiv/Lisans\u00fcst\u00fc/Biyomedikal \u0130\u015faret ve G\u00f6r\u00fcnt\u00fc \u0130\u015fleme/\u00f6devler/2025/\u00f6dev6/kayra/kod.py", "source_location": "L53"}, {"caller_nid": "kayra_kod_save_hist_and_cumulative", "callee": "savefig", "is_member_call": true, "source_file": "/home/kayra/Desktop/YTU_Bilgisayar_Muhendisligi_Arsiv/Lisans\u00fcst\u00fc/Biyomedikal \u0130\u015faret ve G\u00f6r\u00fcnt\u00fc \u0130\u015fleme/\u00f6devler/2025/\u00f6dev6/kayra/kod.py", "source_location": "L54"}, {"caller_nid": "kayra_kod_save_hist_and_cumulative", "callee": "close", "is_member_call": true, "source_file": "/home/kayra/Desktop/YTU_Bilgisayar_Muhendisligi_Arsiv/Lisans\u00fcst\u00fc/Biyomedikal \u0130\u015faret ve G\u00f6r\u00fcnt\u00fc \u0130\u015fleme/\u00f6devler/2025/\u00f6dev6/kayra/kod.py", "source_location": "L55"}, {"caller_nid": "kayra_kod_linear_hist_equalization", "callee": "equalizeHist", "is_member_call": true, "source_file": "/home/kayra/Desktop/YTU_Bilgisayar_Muhendisligi_Arsiv/Lisans\u00fcst\u00fc/Biyomedikal \u0130\u015faret ve G\u00f6r\u00fcnt\u00fc \u0130\u015fleme/\u00f6devler/2025/\u00f6dev6/kayra/kod.py", "source_location": "L59"}, {"caller_nid": "kayra_kod_save_image", "callee": "imwrite", "is_member_call": true, "source_file": "/home/kayra/Desktop/YTU_Bilgisayar_Muhendisligi_Arsiv/Lisans\u00fcst\u00fc/Biyomedikal \u0130\u015faret ve G\u00f6r\u00fcnt\u00fc \u0130\u015fleme/\u00f6devler/2025/\u00f6dev6/kayra/kod.py", "source_location": "L64"}, {"caller_nid": "kayra_kod_histogram_specification", "callee": "histogram", "is_member_call": true, "source_file": "/home/kayra/Desktop/YTU_Bilgisayar_Muhendisligi_Arsiv/Lisans\u00fcst\u00fc/Biyomedikal \u0130\u015faret ve G\u00f6r\u00fcnt\u00fc \u0130\u015fleme/\u00f6devler/2025/\u00f6dev6/kayra/kod.py", "source_location": "L69"}, {"caller_nid": "kayra_kod_histogram_specification", "callee": "flatten", "is_member_call": true, "source_file": "/home/kayra/Desktop/YTU_Bilgisayar_Muhendisligi_Arsiv/Lisans\u00fcst\u00fc/Biyomedikal \u0130\u015faret ve G\u00f6r\u00fcnt\u00fc \u0130\u015fleme/\u00f6devler/2025/\u00f6dev6/kayra/kod.py", "source_location": "L69"}, {"caller_nid": "kayra_kod_histogram_specification", "callee": "histogram", "is_member_call": true, "source_file": "/home/kayra/Desktop/YTU_Bilgisayar_Muhendisligi_Arsiv/Lisans\u00fcst\u00fc/Biyomedikal \u0130\u015faret ve G\u00f6r\u00fcnt\u00fc \u0130\u015fleme/\u00f6devler/2025/\u00f6dev6/kayra/kod.py", "source_location": "L70"}, {"caller_nid": "kayra_kod_histogram_specification", "callee": "flatten", "is_member_call": true, "source_file": "/home/kayra/Desktop/YTU_Bilgisayar_Muhendisligi_Arsiv/Lisans\u00fcst\u00fc/Biyomedikal \u0130\u015faret ve G\u00f6r\u00fcnt\u00fc \u0130\u015fleme/\u00f6devler/2025/\u00f6dev6/kayra/kod.py", "source_location": "L70"}, {"caller_nid": "kayra_kod_histogram_specification", "callee": "astype", "is_member_call": true, "source_file": "/home/kayra/Desktop/YTU_Bilgisayar_Muhendisligi_Arsiv/Lisans\u00fcst\u00fc/Biyomedikal \u0130\u015faret ve G\u00f6r\u00fcnt\u00fc \u0130\u015fleme/\u00f6devler/2025/\u00f6dev6/kayra/kod.py", "source_location": "L72"}, {"caller_nid": "kayra_kod_histogram_specification", "callee": "cumsum", "is_member_call": true, "source_file": "/home/kayra/Desktop/YTU_Bilgisayar_Muhendisligi_Arsiv/Lisans\u00fcst\u00fc/Biyomedikal \u0130\u015faret ve G\u00f6r\u00fcnt\u00fc \u0130\u015fleme/\u00f6devler/2025/\u00f6dev6/kayra/kod.py", "source_location": "L72"}, {"caller_nid": "kayra_kod_histogram_specification", "callee": "astype", "is_member_call": true, "source_file": "/home/kayra/Desktop/YTU_Bilgisayar_Muhendisligi_Arsiv/Lisans\u00fcst\u00fc/Biyomedikal \u0130\u015faret ve G\u00f6r\u00fcnt\u00fc \u0130\u015fleme/\u00f6devler/2025/\u00f6dev6/kayra/kod.py", "source_location": "L73"}, {"caller_nid": "kayra_kod_histogram_specification", "callee": "cumsum", "is_member_call": true, "source_file": "/home/kayra/Desktop/YTU_Bilgisayar_Muhendisligi_Arsiv/Lisans\u00fcst\u00fc/Biyomedikal \u0130\u015faret ve G\u00f6r\u00fcnt\u00fc \u0130\u015fleme/\u00f6devler/2025/\u00f6dev6/kayra/kod.py", "source_location": "L73"}, {"caller_nid": "kayra_kod_histogram_specification", "callee": "zeros", "is_member_call": true, "source_file": "/home/kayra/Desktop/YTU_Bilgisayar_Muhendisligi_Arsiv/Lisans\u00fcst\u00fc/Biyomedikal \u0130\u015faret ve G\u00f6r\u00fcnt\u00fc \u0130\u015fleme/\u00f6devler/2025/\u00f6dev6/kayra/kod.py", "source_location": "L78"}, {"caller_nid": "kayra_kod_main", "callee": "RuntimeError", "is_member_call": false, "source_file": "/home/kayra/Desktop/YTU_Bilgisayar_Muhendisligi_Arsiv/Lisans\u00fcst\u00fc/Biyomedikal \u0130\u015faret ve G\u00f6r\u00fcnt\u00fc \u0130\u015fleme/\u00f6devler/2025/\u00f6dev6/kayra/kod.py", "source_location": "L99"}, {"caller_nid": "kayra_kod_main", "callee": "items", "is_member_call": true, "source_file": "/home/kayra/Desktop/YTU_Bilgisayar_Muhendisligi_Arsiv/Lisans\u00fcst\u00fc/Biyomedikal \u0130\u015faret ve G\u00f6r\u00fcnt\u00fc \u0130\u015fleme/\u00f6devler/2025/\u00f6dev6/kayra/kod.py", "source_location": "L102"}, {"caller_nid": "kayra_kod_main", "callee": "items", "is_member_call": true, "source_file": "/home/kayra/Desktop/YTU_Bilgisayar_Muhendisligi_Arsiv/Lisans\u00fcst\u00fc/Biyomedikal \u0130\u015faret ve G\u00f6r\u00fcnt\u00fc \u0130\u015fleme/\u00f6devler/2025/\u00f6dev6/kayra/kod.py", "source_location": "L109"}, {"caller_nid": "kayra_kod_main", "callee": "keys", "is_member_call": true, "source_file": "/home/kayra/Desktop/YTU_Bilgisayar_Muhendisligi_Arsiv/Lisans\u00fcst\u00fc/Biyomedikal \u0130\u015faret ve G\u00f6r\u00fcnt\u00fc \u0130\u015fleme/\u00f6devler/2025/\u00f6dev6/kayra/kod.py", "source_location": "L115"}]}