{"nodes": [{"id": "home_kayra_desktop_ytu_bilgisayar_muhendisligi_arsiv_3_2_readme_md", "label": "README.md", "file_type": "document", "source_file": "3-2/README.md", "source_location": "L1"}, {"id": "3_2_readme_3_s\u0131n\u0131f_bahar", "label": "\ud83d\udcc5 3. S\u0131n\u0131f Bahar", "file_type": "document", "source_file": "3-2/README.md", "source_location": "L1"}, {"id": "3_2_readme_genel_tavsiyeler", "label": "\ud83d\udcdd Genel Tavsiyeler", "file_type": "document", "source_file": "3-2/README.md", "source_location": "L3"}, {"id": "3_2_readme_d\u00f6nemin_zorunlu_dersleri", "label": "\ud83d\udcda D\u00f6nemin Zorunlu Dersleri", "file_type": "document", "source_file": "3-2/README.md", "source_location": "L8"}, {"id": "3_2_readme_a\u011f_teknolojileri", "label": "\ud83d\udcd8 A\u011f Teknolojileri", "file_type": "document", "source_file": "3-2/README.md", "source_location": "L11"}, {"id": "3_2_readme_ders_bilgileri", "label": "\ud83d\udcc4 Ders Bilgileri", "file_type": "document", "source_file": "3-2/README.md", "source_location": "L13"}, {"id": "3_2_readme_faydal\u0131_olabilecek_kaynaklar", "label": "\ud83d\udcda Faydal\u0131 Olabilecek Kaynaklar", "file_type": "document", "source_file": "3-2/README.md", "source_location": "L38"}, {"id": "3_2_readme_dersi_y\u00fcr\u00fcten_akademisyenler", "label": "\ud83d\udc68\u200d\ud83c\udfeb \ud83d\udc69\u200d\ud83c\udfeb Dersi Y\u00fcr\u00fcten Akademisyenler:", "file_type": "document", "source_file": "3-2/README.md", "source_location": "L44"}, {"id": "3_2_readme_i_dersin_i\u00e7eri\u011fi_g\u00fcncel_de\u011fil", "label": "\u2139\ufe0f Dersin i\u00e7eri\u011fi g\u00fcncel de\u011fil", "file_type": "document", "source_file": "3-2/README.md", "source_location": "L47"}, {"id": "3_2_readme_bilgisayar_projesi", "label": "\ud83d\udcd8 Bilgisayar Projesi", "file_type": "document", "source_file": "3-2/README.md", "source_location": "L50"}, {"id": "3_2_readme_ders_bilgileri_52", "label": "\ud83d\udcc4 Ders Bilgileri", "file_type": "document", "source_file": "3-2/README.md", "source_location": "L52"}, {"id": "3_2_readme_derse_dair_\u00f6neriler", "label": "\ud83d\udca1 Derse Dair \u00d6neriler", "file_type": "document", "source_file": "3-2/README.md", "source_location": "L81"}, {"id": "3_2_readme_\u00f6neri_sahibi_trakt\u00f6r_reis", "label": "\ud83d\udccc \u00d6neri sahibi: Trakt\u00f6r Reis", "file_type": "document", "source_file": "3-2/README.md", "source_location": "L83"}, {"id": "3_2_readme_faydal\u0131_olabilecek_kaynaklar_86", "label": "\ud83d\udcda Faydal\u0131 Olabilecek Kaynaklar", "file_type": "document", "source_file": "3-2/README.md", "source_location": "L86"}, {"id": "3_2_readme_mesleki_hukuk_ve_etik", "label": "\ud83d\udcd8 Mesleki Hukuk ve Etik", "file_type": "document", "source_file": "3-2/README.md", "source_location": "L94"}, {"id": "3_2_readme_ders_bilgileri_96", "label": "\ud83d\udcc4 Ders Bilgileri", "file_type": "document", "source_file": "3-2/README.md", "source_location": "L96"}, {"id": "3_2_readme_faydal\u0131_olabilecek_kaynaklar_117", "label": "\ud83d\udcda Faydal\u0131 Olabilecek Kaynaklar", "file_type": "document", "source_file": "3-2/README.md", "source_location": "L117"}, {"id": "3_2_readme_dersi_y\u00fcr\u00fcten_akademisyenler_122", "label": "\ud83d\udc68\u200d\ud83c\udfeb \ud83d\udc69\u200d\ud83c\udfeb Dersi Y\u00fcr\u00fcten Akademisyenler:", "file_type": "document", "source_file": "3-2/README.md", "source_location": "L122"}, {"id": "3_2_readme_i_dersin_i\u00e7eri\u011fi_g\u00fcncel_de\u011fil_125", "label": "\u2139\ufe0f Dersin i\u00e7eri\u011fi g\u00fcncel de\u011fil", "file_type": "document", "source_file": "3-2/README.md", "source_location": "L125"}, {"id": "3_2_readme_mesleki_staj", "label": "\ud83d\udcd8 Mesleki Staj", "file_type": "document", "source_file": "3-2/README.md", "source_location": "L128"}, {"id": "3_2_readme_ders_bilgileri_130", "label": "\ud83d\udcc4 Ders Bilgileri", "file_type": "document", "source_file": "3-2/README.md", "source_location": "L130"}, {"id": "3_2_readme_faydal\u0131_olabilecek_kaynaklar_151", "label": "\ud83d\udcda Faydal\u0131 Olabilecek Kaynaklar", "file_type": "document", "source_file": "3-2/README.md", "source_location": "L151"}, {"id": "3_2_readme_veri_i\u0307leti\u015fimi_ve_bilgisayar_a\u011flar\u0131", "label": "\ud83d\udcd8 Veri \u0130leti\u015fimi ve Bilgisayar A\u011flar\u0131", "file_type": "document", "source_file": "3-2/README.md", "source_location": "L156"}, {"id": "3_2_readme_ders_bilgileri_158", "label": "\ud83d\udcc4 Ders Bilgileri", "file_type": "document", "source_file": "3-2/README.md", "source_location": "L158"}, {"id": "3_2_readme_faydal\u0131_olabilecek_kaynaklar_179", "label": "\ud83d\udcda Faydal\u0131 Olabilecek Kaynaklar", "file_type": "document", "source_file": "3-2/README.md", "source_location": "L179"}, {"id": "3_2_readme_dersi_y\u00fcr\u00fcten_akademisyenler_188", "label": "\ud83d\udc68\u200d\ud83c\udfeb \ud83d\udc69\u200d\ud83c\udfeb Dersi Y\u00fcr\u00fcten Akademisyenler:", "file_type": "document", "source_file": "3-2/README.md", "source_location": "L188"}, {"id": "3_2_readme_yapay_zeka", "label": "\ud83d\udcd8 Yapay Zeka", "file_type": "document", "source_file": "3-2/README.md", "source_location": "L191"}, {"id": "3_2_readme_ders_bilgileri_193", "label": "\ud83d\udcc4 Ders Bilgileri", "file_type": "document", "source_file": "3-2/README.md", "source_location": "L193"}, {"id": "3_2_readme_faydal\u0131_olabilecek_kaynaklar_219", "label": "\ud83d\udcda Faydal\u0131 Olabilecek Kaynaklar", "file_type": "document", "source_file": "3-2/README.md", "source_location": "L219"}, {"id": "3_2_readme_dersi_y\u00fcr\u00fcten_akademisyenler_229", "label": "\ud83d\udc68\u200d\ud83c\udfeb \ud83d\udc69\u200d\ud83c\udfeb Dersi Y\u00fcr\u00fcten Akademisyenler:", "file_type": "document", "source_file": "3-2/README.md", "source_location": "L229"}, {"id": "3_2_readme_yaz\u0131l\u0131m_m\u00fchendisli\u011fi", "label": "\ud83d\udcd8 Yaz\u0131l\u0131m M\u00fchendisli\u011fi", "file_type": "document", "source_file": "3-2/README.md", "source_location": "L232"}, {"id": "3_2_readme_ders_bilgileri_234", "label": "\ud83d\udcc4 Ders Bilgileri", "file_type": "document", "source_file": "3-2/README.md", "source_location": "L234"}, {"id": "3_2_readme_faydal\u0131_olabilecek_kaynaklar_259", "label": "\ud83d\udcda Faydal\u0131 Olabilecek Kaynaklar", "file_type": "document", "source_file": "3-2/README.md", "source_location": "L259"}, {"id": "3_2_readme_dersi_y\u00fcr\u00fcten_akademisyenler_266", "label": "\ud83d\udc68\u200d\ud83c\udfeb \ud83d\udc69\u200d\ud83c\udfeb Dersi Y\u00fcr\u00fcten Akademisyenler:", "file_type": "document", "source_file": "3-2/README.md", "source_location": "L266"}], "edges": [{"source": "home_kayra_desktop_ytu_bilgisayar_muhendisligi_arsiv_3_2_readme_md", "target": "3_2_readme_3_s\u0131n\u0131f_bahar", "relation": "contains", "confidence": "EXTRACTED", "source_file": "3-2/README.md", "source_location": "L1", "weight": 1.0}, {"source": "3_2_readme_3_s\u0131n\u0131f_bahar", "target": "3_2_readme_genel_tavsiyeler", "relation": "contains", "confidence": "EXTRACTED", "source_file": "3-2/README.md", "source_location": "L3", "weight": 1.0}, {"source": "3_2_readme_3_s\u0131n\u0131f_bahar", "target": "3_2_readme_d\u00f6nemin_zorunlu_dersleri", "relation": "contains", "confidence": "EXTRACTED", "source_file": "3-2/README.md", "source_location": "L8", "weight": 1.0}, {"source": "3_2_readme_d\u00f6nemin_zorunlu_dersleri", "target": "3_2_readme_a\u011f_teknolojileri", "relation": "contains", "confidence": "EXTRACTED", "source_file": "3-2/README.md", "source_location": "L11", "weight": 1.0}, {"source": "3_2_readme_a\u011f_teknolojileri", "target": "3_2_readme_ders_bilgileri", "relation": "contains", "confidence": "EXTRACTED", "source_file": "3-2/README.md", "source_location": "L13", "weight": 1.0}, {"source": "3_2_readme_a\u011f_teknolojileri", "target": "3_2_readme_faydal\u0131_olabilecek_kaynaklar", "relation": "contains", "confidence": "EXTRACTED", "source_file": "3-2/README.md", "source_location": "L38", "weight": 1.0}, {"source": "3_2_readme_a\u011f_teknolojileri", "target": "3_2_readme_dersi_y\u00fcr\u00fcten_akademisyenler", "relation": "contains", "confidence": "EXTRACTED", "source_file": "3-2/README.md", "source_location": "L44", "weight": 1.0}, {"source": "3_2_readme_a\u011f_teknolojileri", "target": "3_2_readme_i_dersin_i\u00e7eri\u011fi_g\u00fcncel_de\u011fil", "relation": "contains", "confidence": "EXTRACTED", "source_file": "3-2/README.md", "source_location": "L47", "weight": 1.0}, {"source": "3_2_readme_d\u00f6nemin_zorunlu_dersleri", "target": "3_2_readme_bilgisayar_projesi", "relation": "contains", "confidence": "EXTRACTED", "source_file": "3-2/README.md", "source_location": "L50", "weight": 1.0}, {"source": "3_2_readme_bilgisayar_projesi", "target": "3_2_readme_ders_bilgileri_52", "relation": "contains", "confidence": "EXTRACTED", "source_file": "3-2/README.md", "source_location": "L52", "weight": 1.0}, {"source": "3_2_readme_bilgisayar_projesi", "target": "3_2_readme_derse_dair_\u00f6neriler", "relation": "contains", "confidence": "EXTRACTED", "source_file": "3-2/README.md", "source_location": "L81", "weight": 1.0}, {"source": "3_2_readme_derse_dair_\u00f6neriler", "target": "3_2_readme_\u00f6neri_sahibi_trakt\u00f6r_reis", "relation": "contains", "confidence": "EXTRACTED", "source_file": "3-2/README.md", "source_location": "L83", "weight": 1.0}, {"source": "3_2_readme_bilgisayar_projesi", "target": "3_2_readme_faydal\u0131_olabilecek_kaynaklar_86", "relation": "contains", "confidence": "EXTRACTED", "source_file": "3-2/README.md", "source_location": "L86", "weight": 1.0}, {"source": "3_2_readme_d\u00f6nemin_zorunlu_dersleri", "target": "3_2_readme_mesleki_hukuk_ve_etik", "relation": "contains", "confidence": "EXTRACTED", "source_file": "3-2/README.md", "source_location": "L94", "weight": 1.0}, {"source": "3_2_readme_mesleki_hukuk_ve_etik", "target": "3_2_readme_ders_bilgileri_96", "relation": "contains", "confidence": "EXTRACTED", "source_file": "3-2/README.md", "source_location": "L96", "weight": 1.0}, {"source": "3_2_readme_mesleki_hukuk_ve_etik", "target": "3_2_readme_faydal\u0131_olabilecek_kaynaklar_117", "relation": "contains", "confidence": "EXTRACTED", "source_file": "3-2/README.md", "source_location": "L117", "weight": 1.0}, {"source": "3_2_readme_mesleki_hukuk_ve_etik", "target": "3_2_readme_dersi_y\u00fcr\u00fcten_akademisyenler_122", "relation": "contains", "confidence": "EXTRACTED", "source_file": "3-2/README.md", "source_location": "L122", "weight": 1.0}, {"source": "3_2_readme_mesleki_hukuk_ve_etik", "target": "3_2_readme_i_dersin_i\u00e7eri\u011fi_g\u00fcncel_de\u011fil_125", "relation": "contains", "confidence": "EXTRACTED", "source_file": "3-2/README.md", "source_location": "L125", "weight": 1.0}, {"source": "3_2_readme_d\u00f6nemin_zorunlu_dersleri", "target": "3_2_readme_mesleki_staj", "relation": "contains", "confidence": "EXTRACTED", "source_file": "3-2/README.md", "source_location": "L128", "weight": 1.0}, {"source": "3_2_readme_mesleki_staj", "target": "3_2_readme_ders_bilgileri_130", "relation": "contains", "confidence": "EXTRACTED", "source_file": "3-2/README.md", "source_location": "L130", "weight": 1.0}, {"source": "3_2_readme_mesleki_staj", "target": "3_2_readme_faydal\u0131_olabilecek_kaynaklar_151", "relation": "contains", "confidence": "EXTRACTED", "source_file": "3-2/README.md", "source_location": "L151", "weight": 1.0}, {"source": "3_2_readme_d\u00f6nemin_zorunlu_dersleri", "target": "3_2_readme_veri_i\u0307leti\u015fimi_ve_bilgisayar_a\u011flar\u0131", "relation": "contains", "confidence": "EXTRACTED", "source_file": "3-2/README.md", "source_location": "L156", "weight": 1.0}, {"source": "3_2_readme_veri_i\u0307leti\u015fimi_ve_bilgisayar_a\u011flar\u0131", "target": "3_2_readme_ders_bilgileri_158", "relation": "contains", "confidence": "EXTRACTED", "source_file": "3-2/README.md", "source_location": "L158", "weight": 1.0}, {"source": "3_2_readme_veri_i\u0307leti\u015fimi_ve_bilgisayar_a\u011flar\u0131", "target": "3_2_readme_faydal\u0131_olabilecek_kaynaklar_179", "relation": "contains", "confidence": "EXTRACTED", "source_file": "3-2/README.md", "source_location": "L179", "weight": 1.0}, {"source": "3_2_readme_veri_i\u0307leti\u015fimi_ve_bilgisayar_a\u011flar\u0131", "target": "3_2_readme_dersi_y\u00fcr\u00fcten_akademisyenler_188", "relation": "contains", "confidence": "EXTRACTED", "source_file": "3-2/README.md", "source_location": "L188", "weight": 1.0}, {"source": "3_2_readme_d\u00f6nemin_zorunlu_dersleri", "target": "3_2_readme_yapay_zeka", "relation": "contains", "confidence": "EXTRACTED", "source_file": "3-2/README.md", "source_location": "L191", "weight": 1.0}, {"source": "3_2_readme_yapay_zeka", "target": "3_2_readme_ders_bilgileri_193", "relation": "contains", "confidence": "EXTRACTED", "source_file": "3-2/README.md", "source_location": "L193", "weight": 1.0}, {"source": "3_2_readme_yapay_zeka", "target": "3_2_readme_faydal\u0131_olabilecek_kaynaklar_219", "relation": "contains", "confidence": "EXTRACTED", "source_file": "3-2/README.md", "source_location": "L219", "weight": 1.0}, {"source": "3_2_readme_yapay_zeka", "target": "3_2_readme_dersi_y\u00fcr\u00fcten_akademisyenler_229", "relation": "contains", "confidence": "EXTRACTED", "source_file": "3-2/README.md", "source_location": "L229", "weight": 1.0}, {"source": "3_2_readme_d\u00f6nemin_zorunlu_dersleri", "target": "3_2_readme_yaz\u0131l\u0131m_m\u00fchendisli\u011fi", "relation": "contains", "confidence": "EXTRACTED", "source_file": "3-2/README.md", "source_location": "L232", "weight": 1.0}, {"source": "3_2_readme_yaz\u0131l\u0131m_m\u00fchendisli\u011fi", "target": "3_2_readme_ders_bilgileri_234", "relation": "contains", "confidence": "EXTRACTED", "source_file": "3-2/README.md", "source_location": "L234", "weight": 1.0}, {"source": "3_2_readme_yaz\u0131l\u0131m_m\u00fchendisli\u011fi", "target": "3_2_readme_faydal\u0131_olabilecek_kaynaklar_259", "relation": "contains", "confidence": "EXTRACTED", "source_file": "3-2/README.md", "source_location": "L259", "weight": 1.0}, {"source": "3_2_readme_yaz\u0131l\u0131m_m\u00fchendisli\u011fi", "target": "3_2_readme_dersi_y\u00fcr\u00fcten_akademisyenler_266", "relation": "contains", "confidence": "EXTRACTED", "source_file": "3-2/README.md", "source_location": "L266", "weight": 1.0}], "input_tokens": 0, "output_tokens": 0}